{
    "@context": [
        "http://iiif.io/api/presentation/2/context.json",
        "http://codh.rois.ac.jp/iiif/curation/1/context.json"
    ],
    "@id": "https://nakamura196.github.io/narita/json/51e05259844db46d4271cbf9fc734ab4.json",
    "@type": "cr:Curation",
    "label": "星鳳樓帖#03#黃甘帖_(王羲之)@東京大学",
    "selections": [
        {
            "@id": "https://nakamura196.github.io/narita/json/51e05259844db46d4271cbf9fc734ab4.json/range1",
            "@type": "sc:Range",
            "label": "Manual curation by IIIF Curation Viewer",
            "members": [
                {
                    "@id": "https://iiif.dl.itc.u-tokyo.ac.jp/repo/iiif/167778/canvas/p14#xywh=1197,827,2278,4779",
                    "@type": "sc:Canvas",
                    "label": 14
                }
            ],
            "within": {
                "@id": "https://diyhistory.org/uparl/omeka/oa/collections/4/manifest.json",
                "@label": "星鳳楼帖 寅 [A005935-03]",
                "@type": "sc:Manifest"
            }
        }
    ]
}