{
    "@context": [
        "http://iiif.io/api/presentation/2/context.json",
        "http://codh.rois.ac.jp/iiif/curation/1/context.json"
    ],
    "@id": "https://nakamura196.github.io/narita/json/61b2dddf7228489da31c644de5eaea4b.json",
    "@type": "cr:Curation",
    "label": "淳化閣帖#08#遇信帖_(王羲之)@東京大学",
    "selections": [
        {
            "@id": "https://nakamura196.github.io/narita/json/61b2dddf7228489da31c644de5eaea4b.json/range1",
            "@type": "sc:Range",
            "label": "Manual curation by IIIF Curation Viewer",
            "members": [
                {
                    "@id": "https://iiif.dl.itc.u-tokyo.ac.jp/repo/iiif/167821/canvas/p3#xywh=408,459,662,5188",
                    "@type": "sc:Canvas",
                    "label": 3
                },
                {
                    "@id": "https://iiif.dl.itc.u-tokyo.ac.jp/repo/iiif/167821/canvas/p4#xywh=5264,481,642,5266",
                    "@type": "sc:Canvas",
                    "label": 4
                }
            ],
            "within": {
                "@id": "https://diyhistory.org/uparl/omeka/oa/collections/47/manifest.json",
                "@label": "泉州本淳化閣帖 八 [A006099-05]",
                "@type": "sc:Manifest"
            }
        }
    ]
}